LICENSE
MANIFEST.in
README.md
requirements.txt
setup.py
fdg/__init__.py
fdg/__version__.py
fdg/expression_slot.py
fdg/fdg_pruner.py
fdg/function_coverage.py
fdg/fwrg_manager.py
fdg/global_config.py
fdg/instruction_modification.py
fdg/output_data.py
fdg/utils.py
fdg/control/__init__.py
fdg/control/ftn_search_strategy.py
fdg/control/function_assignment.py
fdg/control/guider.py
fdg/control/mine.py
fdg/control/weight_computation.py
fdg/preprocessing/__init__.py
fdg/preprocessing/address_collection.py
fdg/preprocessing/instruction_coverage.py
fdg/preprocessing/preprocess.py
fdg/preprocessing/read_in_conditions.py
fdg/preprocessing/slot_location.py
fdg/preprocessing/write_read_info.py
mythril/__init__.py
mythril/__main__.py
mythril/__version__.py
mythril/exceptions.py
mythril/analysis/__init__.py
mythril/analysis/analysis_args.py
mythril/analysis/call_helpers.py
mythril/analysis/callgraph.py
mythril/analysis/issue_annotation.py
mythril/analysis/ops.py
mythril/analysis/potential_issues.py
mythril/analysis/report.py
mythril/analysis/security.py
mythril/analysis/solver.py
mythril/analysis/swc_data.py
mythril/analysis/symbolic.py
mythril/analysis/traceexplore.py
mythril/analysis/module/__init__.py
mythril/analysis/module/base.py
mythril/analysis/module/loader.py
mythril/analysis/module/module_helpers.py
mythril/analysis/module/util.py
mythril/analysis/module/modules/__init__.py
mythril/analysis/module/modules/arbitrary_jump.py
mythril/analysis/module/modules/arbitrary_write.py
mythril/analysis/module/modules/delegatecall.py
mythril/analysis/module/modules/dependence_on_origin.py
mythril/analysis/module/modules/dependence_on_predictable_vars.py
mythril/analysis/module/modules/ether_thief.py
mythril/analysis/module/modules/exceptions.py
mythril/analysis/module/modules/external_calls.py
mythril/analysis/module/modules/integer.py
mythril/analysis/module/modules/multiple_sends.py
mythril/analysis/module/modules/state_change_external_calls.py
smartExecutorx.egg-info/PKG-INFO
smartExecutorx.egg-info/SOURCES.txt
smartExecutorx.egg-info/dependency_links.txt
smartExecutorx.egg-info/entry_points.txt
smartExecutorx.egg-info/requires.txt
smartExecutorx.egg-info/top_level.txt
