Metadata-Version: 2.1
Name: smartExecutorx
Version: 4.1
Summary: Security analysis tool for Ethereum smart contracts
Home-page: https://github.com/contractAnalysis/smartExecutor
Author: contractAnalysis
License: MIT
Keywords: hacking disassembler security ethereum
Classifier: Development Status :: 3 - Alpha
Classifier: Intended Audience :: Science/Research
Classifier: Topic :: Software Development :: Disassemblers
Classifier: License :: OSI Approved :: MIT License
Classifier: Programming Language :: Python :: 3.6
Classifier: Programming Language :: Python :: 3.7
Requires-Python: >=3.8.0
License-File: LICENSE
